[
  {
    "game_id": "20251007-LAK-COL",
    "game_time_utc": "2025-10-08 02:30:00+00:00",
    "game_date": "2025-10-07",
    "final": "Final",
    "outcome": "loss",
    "location": "Home",
    "score": [
      1,
      4
    ],
    "opponent": {
      "id": "COL",
      "name": "Colorado Avalanche",
      "stats": {
        "gp": 79,
        "w": 52,
        "l": 16,
        "t": 0,
        "otl": 11,
        "pts": 115,
        "pct": 0.72785,
        "stk": "OT1",
        "gf": 295,
        "ga": 201,
        "gd": 94
      }
    }
  },
  {
    "game_id": "20251008-VGK-LAK",
    "game_time_utc": "2025-10-09 02:00:00+00:00",
    "game_date": "2025-10-08",
    "final": "Final/SO",
    "location": "Away",
    "outcome": "win",
    "score": [
      6,
      5
    ],
    "opponent": {
      "id": "VGK",
      "name": "Vegas Golden Knights",
      "stats": {
        "gp": 80,
        "w": 37,
        "l": 26,
        "t": 0,
        "otl": 17,
        "pts": 91,
        "pct": 0.56875,
        "stk": "W1",
        "gf": 255,
        "ga": 247,
        "gd": 8
      }
    }
  },
  {
    "game_id": "20251011-WPG-LAK",
    "game_time_utc": "2025-10-11 17:30:00+00:00",
    "game_date": "2025-10-11",
    "final": "Final",
    "location": "Away",
    "outcome": "loss",
    "score": [
      2,
      3
    ],
    "opponent": {
      "id": "WPG",
      "name": "Winnipeg Jets",
      "stats": {
        "gp": 79,
        "w": 35,
        "l": 32,
        "t": 0,
        "otl": 12,
        "pts": 82,
        "pct": 0.51899,
        "stk": "L1",
        "gf": 225,
        "ga": 243,
        "gd": -18
      }
    }
  },
  {
    "game_id": "20251013-MIN-LAK",
    "game_time_utc": "2025-10-14 00:00:00+00:00",
    "game_date": "2025-10-13",
    "final": "Final/SO",
    "location": "Away",
    "outcome": "loss",
    "score": [
      3,
      4
    ],
    "opponent": {
      "id": "MIN",
      "name": "Minnesota Wild",
      "stats": {
        "gp": 80,
        "w": 45,
        "l": 23,
        "t": 0,
        "otl": 12,
        "pts": 102,
        "pct": 0.6375,
        "stk": "L2",
        "gf": 266,
        "ga": 232,
        "gd": 34
      }
    }
  },
  {
    "game_id": "20251016-LAK-PIT",
    "game_time_utc": "2025-10-17 02:00:00+00:00",
    "game_date": "2025-10-16",
    "final": "Final",
    "outcome": "loss",
    "location": "Home",
    "score": [
      2,
      4
    ],
    "opponent": {
      "id": "PIT",
      "name": "Pittsburgh Penguins",
      "stats": {
        "gp": 81,
        "w": 41,
        "l": 24,
        "t": 0,
        "otl": 16,
        "pts": 98,
        "pct": 0.60494,
        "stk": "L2",
        "gf": 288,
        "ga": 261,
        "gd": 27
      }
    }
  },
  {
    "game_id": "20251018-LAK-CAR",
    "game_time_utc": "2025-10-19 01:00:00+00:00",
    "game_date": "2025-10-18",
    "final": "Final/OT",
    "outcome": "loss",
    "location": "Home",
    "score": [
      3,
      4
    ],
    "opponent": {
      "id": "CAR",
      "name": "Carolina Hurricanes",
      "stats": {
        "gp": 80,
        "w": 52,
        "l": 22,
        "t": 0,
        "otl": 6,
        "pts": 110,
        "pct": 0.6875,
        "stk": "W3",
        "gf": 292,
        "ga": 236,
        "gd": 56
      }
    }
  },
  {
    "game_id": "20251021-STL-LAK",
    "game_time_utc": "2025-10-22 00:00:00+00:00",
    "game_date": "2025-10-21",
    "final": "Final/OT",
    "location": "Away",
    "outcome": "win",
    "score": [
      2,
      1
    ],
    "opponent": {
      "id": "STL",
      "name": "St. Louis Blues",
      "stats": {
        "gp": 79,
        "w": 34,
        "l": 33,
        "t": 0,
        "otl": 12,
        "pts": 80,
        "pct": 0.50633,
        "stk": "W1",
        "gf": 213,
        "ga": 247,
        "gd": -34
      }
    }
  },
  {
    "game_id": "20251023-DAL-LAK",
    "game_time_utc": "2025-10-24 01:00:00+00:00",
    "game_date": "2025-10-23",
    "final": "Final/OT",
    "location": "Away",
    "outcome": "win",
    "score": [
      3,
      2
    ],
    "opponent": {
      "id": "DAL",
      "name": "Dallas Stars",
      "stats": {
        "gp": 80,
        "w": 48,
        "l": 20,
        "t": 0,
        "otl": 12,
        "pts": 108,
        "pct": 0.675,
        "stk": "W3",
        "gf": 269,
        "ga": 218,
        "gd": 51
      }
    }
  },
  {
    "game_id": "20251025-NSH-LAK",
    "game_time_utc": "2025-10-26 00:00:00+00:00",
    "game_date": "2025-10-25",
    "final": "Final/SO",
    "location": "Away",
    "outcome": "loss",
    "score": [
      4,
      5
    ],
    "opponent": {
      "id": "NSH",
      "name": "Nashville Predators",
      "stats": {
        "gp": 80,
        "w": 38,
        "l": 32,
        "t": 0,
        "otl": 10,
        "pts": 86,
        "pct": 0.5375,
        "stk": "W1",
        "gf": 241,
        "ga": 261,
        "gd": -20
      }
    }
  },
  {
    "game_id": "20251026-CHI-LAK",
    "game_time_utc": "2025-10-26 23:00:00+00:00",
    "game_date": "2025-10-26",
    "final": "Final",
    "location": "Away",
    "outcome": "win",
    "score": [
      3,
      1
    ],
    "opponent": {
      "id": "CHI",
      "name": "Chicago Blackhawks",
      "stats": {
        "gp": 80,
        "w": 28,
        "l": 38,
        "t": 0,
        "otl": 14,
        "pts": 70,
        "pct": 0.4375,
        "stk": "L3",
        "gf": 207,
        "ga": 268,
        "gd": -61
      }
    }
  },
  {
    "game_id": "20251028-SJS-LAK",
    "game_time_utc": "2025-10-29 03:00:00+00:00",
    "game_date": "2025-10-28",
    "final": "Final",
    "location": "Away",
    "outcome": "win",
    "score": [
      4,
      3
    ],
    "opponent": {
      "id": "SJS",
      "name": "San Jose Sharks",
      "stats": {
        "gp": 79,
        "w": 37,
        "l": 34,
        "t": 0,
        "otl": 8,
        "pts": 82,
        "pct": 0.51899,
        "stk": "OT1",
        "gf": 240,
        "ga": 284,
        "gd": -44
      }
    }
  },
  {
    "game_id": "20251030-LAK-DET",
    "game_time_utc": "2025-10-31 02:30:00+00:00",
    "game_date": "2025-10-30",
    "final": "Final/SO",
    "outcome": "loss",
    "location": "Home",
    "score": [
      3,
      4
    ],
    "opponent": {
      "id": "DET",
      "name": "Detroit Red Wings",
      "stats": {
        "gp": 80,
        "w": 41,
        "l": 30,
        "t": 0,
        "otl": 9,
        "pts": 91,
        "pct": 0.56875,
        "stk": "L1",
        "gf": 237,
        "ga": 246,
        "gd": -9
      }
    }
  },
  {
    "game_id": "20251101-LAK-NJD",
    "game_time_utc": "2025-11-02 01:00:00+00:00",
    "game_date": "2025-11-01",
    "final": "Final",
    "outcome": "loss",
    "location": "Home",
    "score": [
      1,
      4
    ],
    "opponent": {
      "id": "NJD",
      "name": "New Jersey Devils",
      "stats": {
        "gp": 81,
        "w": 42,
        "l": 36,
        "t": 0,
        "otl": 3,
        "pts": 87,
        "pct": 0.53704,
        "stk": "W2",
        "gf": 230,
        "ga": 250,
        "gd": -20
      }
    }
  },
  {
    "game_id": "20251104-LAK-WPG",
    "game_time_utc": "2025-11-05 03:30:00+00:00",
    "game_date": "2025-11-04",
    "final": "Final",
    "outcome": "win",
    "location": "Home",
    "score": [
      3,
      0
    ],
    "opponent": {
      "id": "WPG",
      "name": "Winnipeg Jets",
      "stats": {
        "gp": 79,
        "w": 35,
        "l": 32,
        "t": 0,
        "otl": 12,
        "pts": 82,
        "pct": 0.51899,
        "stk": "L1",
        "gf": 225,
        "ga": 243,
        "gd": -18
      }
    }
  },
  {
    "game_id": "20251106-LAK-FLA",
    "game_time_utc": "2025-11-07 03:00:00+00:00",
    "game_date": "2025-11-06",
    "final": "Final",
    "outcome": "loss",
    "location": "Home",
    "score": [
      2,
      5
    ],
    "opponent": {
      "id": "FLA",
      "name": "Florida Panthers",
      "stats": {
        "gp": 80,
        "w": 38,
        "l": 38,
        "t": 0,
        "otl": 4,
        "pts": 80,
        "pct": 0.5,
        "stk": "W1",
        "gf": 240,
        "ga": 273,
        "gd": -33
      }
    }
  },
  {
    "game_id": "20251109-PIT-LAK",
    "game_time_utc": "2025-11-09 19:00:00+00:00",
    "game_date": "2025-11-09",
    "final": "Final",
    "location": "Away",
    "outcome": "win",
    "score": [
      3,
      2
    ],
    "opponent": {
      "id": "PIT",
      "name": "Pittsburgh Penguins",
      "stats": {
        "gp": 81,
        "w": 41,
        "l": 24,
        "t": 0,
        "otl": 16,
        "pts": 98,
        "pct": 0.60494,
        "stk": "L2",
        "gf": 288,
        "ga": 261,
        "gd": 27
      }
    }
  },
  {
    "game_id": "20251111-MTL-LAK",
    "game_time_utc": "2025-11-12 00:00:00+00:00",
    "game_date": "2025-11-11",
    "final": "Final",
    "location": "Away",
    "outcome": "win",
    "score": [
      5,
      1
    ],
    "opponent": {
      "id": "MTL",
      "name": "Montreal Canadiens",
      "stats": {
        "gp": 81,
        "w": 48,
        "l": 23,
        "t": 0,
        "otl": 10,
        "pts": 106,
        "pct": 0.65432,
        "stk": "W1",
        "gf": 281,
        "ga": 252,
        "gd": 29
      }
    }
  },
  {
    "game_id": "20251113-TOR-LAK",
    "game_time_utc": "2025-11-14 00:00:00+00:00",
    "game_date": "2025-11-13",
    "final": "Final/OT",
    "location": "Away",
    "outcome": "win",
    "score": [
      4,
      3
    ],
    "opponent": {
      "id": "TOR",
      "name": "Toronto Maple Leafs",
      "stats": {
        "gp": 80,
        "w": 32,
        "l": 34,
        "t": 0,
        "otl": 14,
        "pts": 78,
        "pct": 0.4875,
        "stk": "L3",
        "gf": 247,
        "ga": 290,
        "gd": -43
      }
    }
  },
  {
    "game_id": "20251115-OTT-LAK",
    "game_time_utc": "2025-11-16 00:00:00+00:00",
    "game_date": "2025-11-15",
    "final": "Final",
    "location": "Away",
    "outcome": "win",
    "score": [
      1,
      0
    ],
    "opponent": {
      "id": "OTT",
      "name": "Ottawa Senators",
      "stats": {
        "gp": 81,
        "w": 43,
        "l": 27,
        "t": 0,
        "otl": 11,
        "pts": 97,
        "pct": 0.59877,
        "stk": "OT1",
        "gf": 275,
        "ga": 245,
        "gd": 30
      }
    }
  },
  {
    "game_id": "20251117-WSH-LAK",
    "game_time_utc": "2025-11-18 00:00:00+00:00",
    "game_date": "2025-11-17",
    "final": "Final",
    "location": "Away",
    "outcome": "loss",
    "score": [
      1,
      2
    ],
    "opponent": {
      "id": "WSH",
      "name": "Washington Capitals",
      "stats": {
        "gp": 81,
        "w": 42,
        "l": 30,
        "t": 0,
        "otl": 9,
        "pts": 93,
        "pct": 0.57407,
        "stk": "W3",
        "gf": 261,
        "ga": 243,
        "gd": 18
      }
    }
  },
  {
    "game_id": "20251120-SJS-LAK",
    "game_time_utc": "2025-11-21 03:00:00+00:00",
    "game_date": "2025-11-20",
    "final": "Final/SO",
    "location": "Away",
    "outcome": "loss",
    "score": [
      3,
      4
    ],
    "opponent": {
      "id": "SJS",
      "name": "San Jose Sharks",
      "stats": {
        "gp": 79,
        "w": 37,
        "l": 34,
        "t": 0,
        "otl": 8,
        "pts": 82,
        "pct": 0.51899,
        "stk": "OT1",
        "gf": 240,
        "ga": 284,
        "gd": -44
      }
    }
  },
  {
    "game_id": "20251121-LAK-BOS",
    "game_time_utc": "2025-11-22 03:30:00+00:00",
    "game_date": "2025-11-21",
    "final": "Final/OT",
    "outcome": "loss",
    "location": "Home",
    "score": [
      1,
      2
    ],
    "opponent": {
      "id": "BOS",
      "name": "Boston Bruins",
      "stats": {
        "gp": 81,
        "w": 44,
        "l": 27,
        "t": 0,
        "otl": 10,
        "pts": 98,
        "pct": 0.60494,
        "stk": "W1",
        "gf": 268,
        "ga": 250,
        "gd": 18
      }
    }
  },
  {
    "game_id": "20251124-LAK-OTT",
    "game_time_utc": "2025-11-25 02:00:00+00:00",
    "game_date": "2025-11-24",
    "final": "Final",
    "outcome": "win",
    "location": "Home",
    "score": [
      2,
      1
    ],
    "opponent": {
      "id": "OTT",
      "name": "Ottawa Senators",
      "stats": {
        "gp": 81,
        "w": 43,
        "l": 27,
        "t": 0,
        "otl": 11,
        "pts": 97,
        "pct": 0.59877,
        "stk": "OT1",
        "gf": 275,
        "ga": 245,
        "gd": 30
      }
    }
  },
  {
    "game_id": "20251128-ANA-LAK",
    "game_time_utc": "2025-11-28 21:00:00+00:00",
    "game_date": "2025-11-28",
    "final": "Final/SO",
    "location": "Away",
    "outcome": "loss",
    "score": [
      4,
      5
    ],
    "opponent": {
      "id": "ANA",
      "name": "Anaheim Ducks",
      "stats": {
        "gp": 80,
        "w": 42,
        "l": 32,
        "t": 0,
        "otl": 6,
        "pts": 90,
        "pct": 0.5625,
        "stk": "OT1",
        "gf": 266,
        "ga": 281,
        "gd": -15
      }
    }
  },
  {
    "game_id": "20251129-LAK-VAN",
    "game_time_utc": "2025-11-30 03:00:00+00:00",
    "game_date": "2025-11-29",
    "final": "Final/OT",
    "outcome": "win",
    "location": "Home",
    "score": [
      2,
      1
    ],
    "opponent": {
      "id": "VAN",
      "name": "Vancouver Canucks",
      "stats": {
        "gp": 80,
        "w": 24,
        "l": 48,
        "t": 0,
        "otl": 8,
        "pts": 56,
        "pct": 0.35,
        "stk": "W2",
        "gf": 211,
        "ga": 307,
        "gd": -96
      }
    }
  },
  {
    "game_id": "20251202-LAK-WSH",
    "game_time_utc": "2025-12-03 03:30:00+00:00",
    "game_date": "2025-12-02",
    "final": "Final",
    "outcome": "loss",
    "location": "Home",
    "score": [
      1,
      3
    ],
    "opponent": {
      "id": "WSH",
      "name": "Washington Capitals",
      "stats": {
        "gp": 81,
        "w": 42,
        "l": 30,
        "t": 0,
        "otl": 9,
        "pts": 93,
        "pct": 0.57407,
        "stk": "W3",
        "gf": 261,
        "ga": 243,
        "gd": 18
      }
    }
  },
  {
    "game_id": "20251204-LAK-CHI",
    "game_time_utc": "2025-12-05 03:00:00+00:00",
    "game_date": "2025-12-04",
    "final": "Final",
    "outcome": "loss",
    "location": "Home",
    "score": [
      1,
      2
    ],
    "opponent": {
      "id": "CHI",
      "name": "Chicago Blackhawks",
      "stats": {
        "gp": 80,
        "w": 28,
        "l": 38,
        "t": 0,
        "otl": 14,
        "pts": 70,
        "pct": 0.4375,
        "stk": "L3",
        "gf": 207,
        "ga": 268,
        "gd": -61
      }
    }
  },
  {
    "game_id": "20251206-LAK-CHI",
    "game_time_utc": "2025-12-07 02:00:00+00:00",
    "game_date": "2025-12-06",
    "final": "Final",
    "outcome": "win",
    "location": "Home",
    "score": [
      6,
      0
    ],
    "opponent": {
      "id": "CHI",
      "name": "Chicago Blackhawks",
      "stats": {
        "gp": 80,
        "w": 28,
        "l": 38,
        "t": 0,
        "otl": 14,
        "pts": 70,
        "pct": 0.4375,
        "stk": "L3",
        "gf": 207,
        "ga": 268,
        "gd": -61
      }
    }
  },
  {
    "game_id": "20251208-UTA-LAK",
    "game_time_utc": "2025-12-09 02:00:00+00:00",
    "game_date": "2025-12-08",
    "final": "Final",
    "location": "Away",
    "outcome": "win",
    "score": [
      4,
      2
    ],
    "opponent": {
      "id": "UTA",
      "name": "Utah Mammoth",
      "stats": {
        "gp": 80,
        "w": 42,
        "l": 32,
        "t": 0,
        "otl": 6,
        "pts": 90,
        "pct": 0.5625,
        "stk": "L2",
        "gf": 260,
        "ga": 232,
        "gd": 28
      }
    }
  },
  {
    "game_id": "20251210-SEA-LAK",
    "game_time_utc": "2025-12-11 03:00:00+00:00",
    "game_date": "2025-12-10",
    "final": "Final/OT",
    "location": "Away",
    "outcome": "loss",
    "score": [
      2,
      3
    ],
    "opponent": {
      "id": "SEA",
      "name": "Seattle Kraken",
      "stats": {
        "gp": 79,
        "w": 34,
        "l": 34,
        "t": 0,
        "otl": 11,
        "pts": 79,
        "pct": 0.5,
        "stk": "W2",
        "gf": 222,
        "ga": 252,
        "gd": -30
      }
    }
  },
  {
    "game_id": "20251213-LAK-CGY",
    "game_time_utc": "2025-12-14 03:00:00+00:00",
    "game_date": "2025-12-13",
    "final": "Final/OT",
    "outcome": "loss",
    "location": "Home",
    "score": [
      1,
      2
    ],
    "opponent": {
      "id": "CGY",
      "name": "Calgary Flames",
      "stats": {
        "gp": 80,
        "w": 33,
        "l": 38,
        "t": 0,
        "otl": 9,
        "pts": 75,
        "pct": 0.46875,
        "stk": "W1",
        "gf": 208,
        "ga": 255,
        "gd": -47
      }
    }
  },
  {
    "game_id": "20251215-DAL-LAK",
    "game_time_utc": "2025-12-16 01:00:00+00:00",
    "game_date": "2025-12-15",
    "final": "Final",
    "location": "Away",
    "outcome": "loss",
    "score": [
      1,
      4
    ],
    "opponent": {
      "id": "DAL",
      "name": "Dallas Stars",
      "stats": {
        "gp": 80,
        "w": 48,
        "l": 20,
        "t": 0,
        "otl": 12,
        "pts": 108,
        "pct": 0.675,
        "stk": "W3",
        "gf": 269,
        "ga": 218,
        "gd": 51
      }
    }
  },
  {
    "game_id": "20251217-FLA-LAK",
    "game_time_utc": "2025-12-18 00:00:00+00:00",
    "game_date": "2025-12-17",
    "final": "Final",
    "location": "Away",
    "outcome": "loss",
    "score": [
      2,
      3
    ],
    "opponent": {
      "id": "FLA",
      "name": "Florida Panthers",
      "stats": {
        "gp": 80,
        "w": 38,
        "l": 38,
        "t": 0,
        "otl": 4,
        "pts": 80,
        "pct": 0.5,
        "stk": "W1",
        "gf": 240,
        "ga": 273,
        "gd": -33
      }
    }
  },
  {
    "game_id": "20251218-TBL-LAK",
    "game_time_utc": "2025-12-19 00:00:00+00:00",
    "game_date": "2025-12-18",
    "final": "Final",
    "location": "Away",
    "outcome": "win",
    "score": [
      2,
      1
    ],
    "opponent": {
      "id": "TBL",
      "name": "Tampa Bay Lightning",
      "stats": {
        "gp": 80,
        "w": 49,
        "l": 25,
        "t": 0,
        "otl": 6,
        "pts": 104,
        "pct": 0.65,
        "stk": "W1",
        "gf": 284,
        "ga": 224,
        "gd": 60
      }
    }
  },
  {
    "game_id": "20251222-LAK-CBJ",
    "game_time_utc": "2025-12-23 03:00:00+00:00",
    "game_date": "2025-12-22",
    "final": "Final",
    "outcome": "loss",
    "location": "Home",
    "score": [
      1,
      3
    ],
    "opponent": {
      "id": "CBJ",
      "name": "Columbus Blue Jackets",
      "stats": {
        "gp": 81,
        "w": 40,
        "l": 29,
        "t": 0,
        "otl": 12,
        "pts": 92,
        "pct": 0.5679,
        "stk": "L1",
        "gf": 252,
        "ga": 251,
        "gd": 1
      }
    }
  },
  {
    "game_id": "20251223-LAK-SEA",
    "game_time_utc": "2025-12-24 03:00:00+00:00",
    "game_date": "2025-12-23",
    "final": "Final",
    "outcome": "loss",
    "location": "Home",
    "score": [
      2,
      3
    ],
    "opponent": {
      "id": "SEA",
      "name": "Seattle Kraken",
      "stats": {
        "gp": 79,
        "w": 34,
        "l": 34,
        "t": 0,
        "otl": 11,
        "pts": 79,
        "pct": 0.5,
        "stk": "W2",
        "gf": 222,
        "ga": 252,
        "gd": -30
      }
    }
  },
  {
    "game_id": "20251227-LAK-ANA",
    "game_time_utc": "2025-12-28 02:00:00+00:00",
    "game_date": "2025-12-27",
    "final": "Final",
    "outcome": "win",
    "location": "Home",
    "score": [
      6,
      1
    ],
    "opponent": {
      "id": "ANA",
      "name": "Anaheim Ducks",
      "stats": {
        "gp": 80,
        "w": 42,
        "l": 32,
        "t": 0,
        "otl": 6,
        "pts": 90,
        "pct": 0.5625,
        "stk": "OT1",
        "gf": 266,
        "ga": 281,
        "gd": -15
      }
    }
  },
  {
    "game_id": "20251229-COL-LAK",
    "game_time_utc": "2025-12-30 02:00:00+00:00",
    "game_date": "2025-12-29",
    "final": "Final",
    "location": "Away",
    "outcome": "loss",
    "score": [
      2,
      5
    ],
    "opponent": {
      "id": "COL",
      "name": "Colorado Avalanche",
      "stats": {
        "gp": 79,
        "w": 52,
        "l": 16,
        "t": 0,
        "otl": 11,
        "pts": 115,
        "pct": 0.72785,
        "stk": "OT1",
        "gf": 295,
        "ga": 201,
        "gd": 94
      }
    }
  },
  {
    "game_id": "20260101-LAK-TBL",
    "game_time_utc": "2026-01-02 00:00:00+00:00",
    "game_date": "2026-01-01",
    "final": "Final",
    "outcome": "loss",
    "location": "Home",
    "score": [
      3,
      5
    ],
    "opponent": {
      "id": "TBL",
      "name": "Tampa Bay Lightning",
      "stats": {
        "gp": 80,
        "w": 49,
        "l": 25,
        "t": 0,
        "otl": 6,
        "pts": 104,
        "pct": 0.65,
        "stk": "W1",
        "gf": 284,
        "ga": 224,
        "gd": 60
      }
    }
  },
  {
    "game_id": "20260103-LAK-MIN",
    "game_time_utc": "2026-01-04 02:00:00+00:00",
    "game_date": "2026-01-03",
    "final": "Final/SO",
    "outcome": "win",
    "location": "Home",
    "score": [
      5,
      4
    ],
    "opponent": {
      "id": "MIN",
      "name": "Minnesota Wild",
      "stats": {
        "gp": 80,
        "w": 45,
        "l": 23,
        "t": 0,
        "otl": 12,
        "pts": 102,
        "pct": 0.6375,
        "stk": "L2",
        "gf": 266,
        "ga": 232,
        "gd": 34
      }
    }
  },
  {
    "game_id": "20260105-LAK-MIN",
    "game_time_utc": "2026-01-06 03:30:00+00:00",
    "game_date": "2026-01-05",
    "final": "Final",
    "outcome": "win",
    "location": "Home",
    "score": [
      4,
      2
    ],
    "opponent": {
      "id": "MIN",
      "name": "Minnesota Wild",
      "stats": {
        "gp": 80,
        "w": 45,
        "l": 23,
        "t": 0,
        "otl": 12,
        "pts": 102,
        "pct": 0.6375,
        "stk": "L2",
        "gf": 266,
        "ga": 232,
        "gd": 34
      }
    }
  },
  {
    "game_id": "20260107-LAK-SJS",
    "game_time_utc": "2026-01-08 03:30:00+00:00",
    "game_date": "2026-01-07",
    "final": "Final/OT",
    "outcome": "loss",
    "location": "Home",
    "score": [
      3,
      4
    ],
    "opponent": {
      "id": "SJS",
      "name": "San Jose Sharks",
      "stats": {
        "gp": 79,
        "w": 37,
        "l": 34,
        "t": 0,
        "otl": 8,
        "pts": 82,
        "pct": 0.51899,
        "stk": "OT1",
        "gf": 240,
        "ga": 284,
        "gd": -44
      }
    }
  },
  {
    "game_id": "20260109-WPG-LAK",
    "game_time_utc": "2026-01-10 01:00:00+00:00",
    "game_date": "2026-01-09",
    "final": "Final",
    "location": "Away",
    "outcome": "loss",
    "score": [
      1,
      5
    ],
    "opponent": {
      "id": "WPG",
      "name": "Winnipeg Jets",
      "stats": {
        "gp": 79,
        "w": 35,
        "l": 32,
        "t": 0,
        "otl": 12,
        "pts": 82,
        "pct": 0.51899,
        "stk": "L1",
        "gf": 225,
        "ga": 243,
        "gd": -18
      }
    }
  },
  {
    "game_id": "20260110-EDM-LAK",
    "game_time_utc": "2026-01-11 03:00:00+00:00",
    "game_date": "2026-01-10",
    "final": "Final/SO",
    "location": "Away",
    "outcome": "win",
    "score": [
      4,
      3
    ],
    "opponent": {
      "id": "EDM",
      "name": "Edmonton Oilers",
      "stats": {
        "gp": 80,
        "w": 40,
        "l": 30,
        "t": 0,
        "otl": 10,
        "pts": 90,
        "pct": 0.5625,
        "stk": "L1",
        "gf": 275,
        "ga": 266,
        "gd": 9
      }
    }
  },
  {
    "game_id": "20260112-LAK-DAL",
    "game_time_utc": "2026-01-13 03:00:00+00:00",
    "game_date": "2026-01-12",
    "final": "Final",
    "outcome": "loss",
    "location": "Home",
    "score": [
      1,
      3
    ],
    "opponent": {
      "id": "DAL",
      "name": "Dallas Stars",
      "stats": {
        "gp": 80,
        "w": 48,
        "l": 20,
        "t": 0,
        "otl": 12,
        "pts": 108,
        "pct": 0.675,
        "stk": "W3",
        "gf": 269,
        "ga": 218,
        "gd": 51
      }
    }
  },
  {
    "game_id": "20260114-LAK-VGK",
    "game_time_utc": "2026-01-15 03:00:00+00:00",
    "game_date": "2026-01-14",
    "final": "Final/OT",
    "outcome": "loss",
    "location": "Home",
    "score": [
      2,
      3
    ],
    "opponent": {
      "id": "VGK",
      "name": "Vegas Golden Knights",
      "stats": {
        "gp": 80,
        "w": 37,
        "l": 26,
        "t": 0,
        "otl": 17,
        "pts": 91,
        "pct": 0.56875,
        "stk": "W1",
        "gf": 255,
        "ga": 247,
        "gd": 8
      }
    }
  },
  {
    "game_id": "20260116-LAK-ANA",
    "game_time_utc": "2026-01-17 03:30:00+00:00",
    "game_date": "2026-01-16",
    "final": "Final/SO",
    "outcome": "loss",
    "location": "Home",
    "score": [
      2,
      3
    ],
    "opponent": {
      "id": "ANA",
      "name": "Anaheim Ducks",
      "stats": {
        "gp": 80,
        "w": 42,
        "l": 32,
        "t": 0,
        "otl": 6,
        "pts": 90,
        "pct": 0.5625,
        "stk": "OT1",
        "gf": 266,
        "ga": 281,
        "gd": -15
      }
    }
  },
  {
    "game_id": "20260117-ANA-LAK",
    "game_time_utc": "2026-01-18 03:00:00+00:00",
    "game_date": "2026-01-17",
    "final": "Final/OT",
    "location": "Away",
    "outcome": "loss",
    "score": [
      1,
      2
    ],
    "opponent": {
      "id": "ANA",
      "name": "Anaheim Ducks",
      "stats": {
        "gp": 80,
        "w": 42,
        "l": 32,
        "t": 0,
        "otl": 6,
        "pts": 90,
        "pct": 0.5625,
        "stk": "OT1",
        "gf": 266,
        "ga": 281,
        "gd": -15
      }
    }
  },
  {
    "game_id": "20260120-LAK-NYR",
    "game_time_utc": "2026-01-21 03:00:00+00:00",
    "game_date": "2026-01-20",
    "final": "Final",
    "outcome": "win",
    "location": "Home",
    "score": [
      4,
      3
    ],
    "opponent": {
      "id": "NYR",
      "name": "New York Rangers",
      "stats": {
        "gp": 80,
        "w": 33,
        "l": 38,
        "t": 0,
        "otl": 9,
        "pts": 75,
        "pct": 0.46875,
        "stk": "L2",
        "gf": 232,
        "ga": 245,
        "gd": -13
      }
    }
  },
  {
    "game_id": "20260124-STL-LAK",
    "game_time_utc": "2026-01-25 01:00:00+00:00",
    "game_date": "2026-01-24",
    "final": "Final/SO",
    "location": "Away",
    "outcome": "win",
    "score": [
      5,
      4
    ],
    "opponent": {
      "id": "STL",
      "name": "St. Louis Blues",
      "stats": {
        "gp": 79,
        "w": 34,
        "l": 33,
        "t": 0,
        "otl": 12,
        "pts": 80,
        "pct": 0.50633,
        "stk": "W1",
        "gf": 213,
        "ga": 247,
        "gd": -34
      }
    }
  },
  {
    "game_id": "20260127-DET-LAK",
    "game_time_utc": "2026-01-28 00:00:00+00:00",
    "game_date": "2026-01-27",
    "final": "Final",
    "location": "Away",
    "outcome": "win",
    "score": [
      3,
      1
    ],
    "opponent": {
      "id": "DET",
      "name": "Detroit Red Wings",
      "stats": {
        "gp": 80,
        "w": 41,
        "l": 30,
        "t": 0,
        "otl": 9,
        "pts": 91,
        "pct": 0.56875,
        "stk": "L1",
        "gf": 237,
        "ga": 246,
        "gd": -9
      }
    }
  },
  {
    "game_id": "20260129-BUF-LAK",
    "game_time_utc": "2026-01-30 00:00:00+00:00",
    "game_date": "2026-01-29",
    "final": "Final",
    "location": "Away",
    "outcome": "loss",
    "score": [
      1,
      4
    ],
    "opponent": {
      "id": "BUF",
      "name": "Buffalo Sabres",
      "stats": {
        "gp": 80,
        "w": 49,
        "l": 23,
        "t": 0,
        "otl": 8,
        "pts": 106,
        "pct": 0.6625,
        "stk": "W3",
        "gf": 280,
        "ga": 236,
        "gd": 44
      }
    }
  },
  {
    "game_id": "20260131-PHI-LAK",
    "game_time_utc": "2026-01-31 17:30:00+00:00",
    "game_date": "2026-01-31",
    "final": "Final/OT",
    "location": "Away",
    "outcome": "win",
    "score": [
      3,
      2
    ],
    "opponent": {
      "id": "PHI",
      "name": "Philadelphia Flyers",
      "stats": {
        "gp": 80,
        "w": 41,
        "l": 27,
        "t": 0,
        "otl": 12,
        "pts": 94,
        "pct": 0.5875,
        "stk": "W1",
        "gf": 243,
        "ga": 239,
        "gd": 4
      }
    }
  },
  {
    "game_id": "20260201-CAR-LAK",
    "game_time_utc": "2026-02-01 20:00:00+00:00",
    "game_date": "2026-02-01",
    "final": "Final/OT",
    "location": "Away",
    "outcome": "loss",
    "score": [
      2,
      3
    ],
    "opponent": {
      "id": "CAR",
      "name": "Carolina Hurricanes",
      "stats": {
        "gp": 80,
        "w": 52,
        "l": 22,
        "t": 0,
        "otl": 6,
        "pts": 110,
        "pct": 0.6875,
        "stk": "W3",
        "gf": 292,
        "ga": 236,
        "gd": 56
      }
    }
  },
  {
    "game_id": "20260204-LAK-SEA",
    "game_time_utc": "2026-02-05 03:00:00+00:00",
    "game_date": "2026-02-04",
    "final": "Final",
    "outcome": "loss",
    "location": "Home",
    "score": [
      2,
      4
    ],
    "opponent": {
      "id": "SEA",
      "name": "Seattle Kraken",
      "stats": {
        "gp": 79,
        "w": 34,
        "l": 34,
        "t": 0,
        "otl": 11,
        "pts": 79,
        "pct": 0.5,
        "stk": "W2",
        "gf": 222,
        "ga": 252,
        "gd": -30
      }
    }
  },
  {
    "game_id": "20260205-VGK-LAK",
    "game_time_utc": "2026-02-06 03:00:00+00:00",
    "game_date": "2026-02-05",
    "final": "Final",
    "location": "Away",
    "outcome": "loss",
    "score": [
      1,
      4
    ],
    "opponent": {
      "id": "VGK",
      "name": "Vegas Golden Knights",
      "stats": {
        "gp": 80,
        "w": 37,
        "l": 26,
        "t": 0,
        "otl": 17,
        "pts": 91,
        "pct": 0.56875,
        "stk": "W1",
        "gf": 255,
        "ga": 247,
        "gd": 8
      }
    }
  },
  {
    "game_id": "20260225-LAK-VGK",
    "game_time_utc": "2026-02-26 03:00:00+00:00",
    "game_date": "2026-02-25",
    "final": "Final",
    "outcome": "loss",
    "location": "Home",
    "score": [
      4,
      6
    ],
    "opponent": {
      "id": "VGK",
      "name": "Vegas Golden Knights",
      "stats": {
        "gp": 80,
        "w": 37,
        "l": 26,
        "t": 0,
        "otl": 17,
        "pts": 91,
        "pct": 0.56875,
        "stk": "W1",
        "gf": 255,
        "ga": 247,
        "gd": 8
      }
    }
  },
  {
    "game_id": "20260226-LAK-EDM",
    "game_time_utc": "2026-02-27 03:30:00+00:00",
    "game_date": "2026-02-26",
    "final": "Final",
    "outcome": "loss",
    "location": "Home",
    "score": [
      1,
      8
    ],
    "opponent": {
      "id": "EDM",
      "name": "Edmonton Oilers",
      "stats": {
        "gp": 80,
        "w": 40,
        "l": 30,
        "t": 0,
        "otl": 10,
        "pts": 90,
        "pct": 0.5625,
        "stk": "L1",
        "gf": 275,
        "ga": 266,
        "gd": 9
      }
    }
  },
  {
    "game_id": "20260228-LAK-CGY",
    "game_time_utc": "2026-03-01 00:00:00+00:00",
    "game_date": "2026-02-28",
    "final": "Final",
    "outcome": "win",
    "location": "Home",
    "score": [
      2,
      0
    ],
    "opponent": {
      "id": "CGY",
      "name": "Calgary Flames",
      "stats": {
        "gp": 80,
        "w": 33,
        "l": 38,
        "t": 0,
        "otl": 9,
        "pts": 75,
        "pct": 0.46875,
        "stk": "W1",
        "gf": 208,
        "ga": 255,
        "gd": -47
      }
    }
  },
  {
    "game_id": "20260302-LAK-COL",
    "game_time_utc": "2026-03-03 03:30:00+00:00",
    "game_date": "2026-03-02",
    "final": "Final",
    "outcome": "loss",
    "location": "Home",
    "score": [
      2,
      4
    ],
    "opponent": {
      "id": "COL",
      "name": "Colorado Avalanche",
      "stats": {
        "gp": 79,
        "w": 52,
        "l": 16,
        "t": 0,
        "otl": 11,
        "pts": 115,
        "pct": 0.72785,
        "stk": "OT1",
        "gf": 295,
        "ga": 201,
        "gd": 94
      }
    }
  },
  {
    "game_id": "20260305-LAK-NYI",
    "game_time_utc": "2026-03-06 02:30:00+00:00",
    "game_date": "2026-03-05",
    "final": "Final",
    "outcome": "win",
    "location": "Home",
    "score": [
      5,
      3
    ],
    "opponent": {
      "id": "NYI",
      "name": "New York Islanders",
      "stats": {
        "gp": 81,
        "w": 43,
        "l": 33,
        "t": 0,
        "otl": 5,
        "pts": 91,
        "pct": 0.56173,
        "stk": "L2",
        "gf": 232,
        "ga": 239,
        "gd": -7
      }
    }
  },
  {
    "game_id": "20260307-LAK-MTL",
    "game_time_utc": "2026-03-08 00:00:00+00:00",
    "game_date": "2026-03-07",
    "final": "Final",
    "outcome": "loss",
    "location": "Home",
    "score": [
      3,
      4
    ],
    "opponent": {
      "id": "MTL",
      "name": "Montreal Canadiens",
      "stats": {
        "gp": 81,
        "w": 48,
        "l": 23,
        "t": 0,
        "otl": 10,
        "pts": 106,
        "pct": 0.65432,
        "stk": "W1",
        "gf": 281,
        "ga": 252,
        "gd": 29
      }
    }
  },
  {
    "game_id": "20260309-CBJ-LAK",
    "game_time_utc": "2026-03-09 20:00:00+00:00",
    "game_date": "2026-03-09",
    "final": "Final/OT",
    "location": "Away",
    "outcome": "win",
    "score": [
      5,
      4
    ],
    "opponent": {
      "id": "CBJ",
      "name": "Columbus Blue Jackets",
      "stats": {
        "gp": 81,
        "w": 40,
        "l": 29,
        "t": 0,
        "otl": 12,
        "pts": 92,
        "pct": 0.5679,
        "stk": "L1",
        "gf": 252,
        "ga": 251,
        "gd": 1
      }
    }
  },
  {
    "game_id": "20260310-BOS-LAK",
    "game_time_utc": "2026-03-10 23:00:00+00:00",
    "game_date": "2026-03-10",
    "final": "Final/OT",
    "location": "Away",
    "outcome": "loss",
    "score": [
      1,
      2
    ],
    "opponent": {
      "id": "BOS",
      "name": "Boston Bruins",
      "stats": {
        "gp": 81,
        "w": 44,
        "l": 27,
        "t": 0,
        "otl": 10,
        "pts": 98,
        "pct": 0.60494,
        "stk": "W1",
        "gf": 268,
        "ga": 250,
        "gd": 18
      }
    }
  },
  {
    "game_id": "20260313-NYI-LAK",
    "game_time_utc": "2026-03-13 23:00:00+00:00",
    "game_date": "2026-03-13",
    "final": "Final",
    "location": "Away",
    "outcome": "win",
    "score": [
      3,
      2
    ],
    "opponent": {
      "id": "NYI",
      "name": "New York Islanders",
      "stats": {
        "gp": 81,
        "w": 43,
        "l": 33,
        "t": 0,
        "otl": 5,
        "pts": 91,
        "pct": 0.56173,
        "stk": "L2",
        "gf": 232,
        "ga": 239,
        "gd": -7
      }
    }
  },
  {
    "game_id": "20260314-NJD-LAK",
    "game_time_utc": "2026-03-14 23:00:00+00:00",
    "game_date": "2026-03-14",
    "final": "Final",
    "location": "Away",
    "outcome": "loss",
    "score": [
      4,
      6
    ],
    "opponent": {
      "id": "NJD",
      "name": "New Jersey Devils",
      "stats": {
        "gp": 81,
        "w": 42,
        "l": 36,
        "t": 0,
        "otl": 3,
        "pts": 87,
        "pct": 0.53704,
        "stk": "W2",
        "gf": 230,
        "ga": 250,
        "gd": -20
      }
    }
  },
  {
    "game_id": "20260316-NYR-LAK",
    "game_time_utc": "2026-03-16 23:00:00+00:00",
    "game_date": "2026-03-16",
    "final": "Final",
    "location": "Away",
    "outcome": "win",
    "score": [
      4,
      1
    ],
    "opponent": {
      "id": "NYR",
      "name": "New York Rangers",
      "stats": {
        "gp": 80,
        "w": 33,
        "l": 38,
        "t": 0,
        "otl": 9,
        "pts": 75,
        "pct": 0.46875,
        "stk": "L2",
        "gf": 232,
        "ga": 245,
        "gd": -13
      }
    }
  },
  {
    "game_id": "20260319-LAK-PHI",
    "game_time_utc": "2026-03-20 02:30:00+00:00",
    "game_date": "2026-03-19",
    "final": "Final/SO",
    "outcome": "loss",
    "location": "Home",
    "score": [
      3,
      4
    ],
    "opponent": {
      "id": "PHI",
      "name": "Philadelphia Flyers",
      "stats": {
        "gp": 80,
        "w": 41,
        "l": 27,
        "t": 0,
        "otl": 12,
        "pts": 94,
        "pct": 0.5875,
        "stk": "W1",
        "gf": 243,
        "ga": 239,
        "gd": 4
      }
    }
  },
  {
    "game_id": "20260321-LAK-BUF",
    "game_time_utc": "2026-03-21 20:00:00+00:00",
    "game_date": "2026-03-21",
    "final": "Final",
    "outcome": "loss",
    "location": "Home",
    "score": [
      1,
      4
    ],
    "opponent": {
      "id": "BUF",
      "name": "Buffalo Sabres",
      "stats": {
        "gp": 80,
        "w": 49,
        "l": 23,
        "t": 0,
        "otl": 8,
        "pts": 106,
        "pct": 0.6625,
        "stk": "W3",
        "gf": 280,
        "ga": 236,
        "gd": 44
      }
    }
  },
  {
    "game_id": "20260322-UTA-LAK",
    "game_time_utc": "2026-03-23 01:00:00+00:00",
    "game_date": "2026-03-22",
    "final": "Final/OT",
    "location": "Away",
    "outcome": "loss",
    "score": [
      3,
      4
    ],
    "opponent": {
      "id": "UTA",
      "name": "Utah Mammoth",
      "stats": {
        "gp": 80,
        "w": 42,
        "l": 32,
        "t": 0,
        "otl": 6,
        "pts": 90,
        "pct": 0.5625,
        "stk": "L2",
        "gf": 260,
        "ga": 232,
        "gd": 28
      }
    }
  },
  {
    "game_id": "20260324-CGY-LAK",
    "game_time_utc": "2026-03-25 01:00:00+00:00",
    "game_date": "2026-03-24",
    "final": "Final/SO",
    "location": "Away",
    "outcome": "loss",
    "score": [
      2,
      3
    ],
    "opponent": {
      "id": "CGY",
      "name": "Calgary Flames",
      "stats": {
        "gp": 80,
        "w": 33,
        "l": 38,
        "t": 0,
        "otl": 9,
        "pts": 75,
        "pct": 0.46875,
        "stk": "W1",
        "gf": 208,
        "ga": 255,
        "gd": -47
      }
    }
  },
  {
    "game_id": "20260326-VAN-LAK",
    "game_time_utc": "2026-03-27 02:00:00+00:00",
    "game_date": "2026-03-26",
    "final": "Final",
    "location": "Away",
    "outcome": "win",
    "score": [
      4,
      0
    ],
    "opponent": {
      "id": "VAN",
      "name": "Vancouver Canucks",
      "stats": {
        "gp": 80,
        "w": 24,
        "l": 48,
        "t": 0,
        "otl": 8,
        "pts": 56,
        "pct": 0.35,
        "stk": "W2",
        "gf": 211,
        "ga": 307,
        "gd": -96
      }
    }
  },
  {
    "game_id": "20260328-LAK-UTA",
    "game_time_utc": "2026-03-29 01:00:00+00:00",
    "game_date": "2026-03-28",
    "final": "Final",
    "outcome": "loss",
    "location": "Home",
    "score": [
      2,
      6
    ],
    "opponent": {
      "id": "UTA",
      "name": "Utah Mammoth",
      "stats": {
        "gp": 80,
        "w": 42,
        "l": 32,
        "t": 0,
        "otl": 6,
        "pts": 90,
        "pct": 0.5625,
        "stk": "L2",
        "gf": 260,
        "ga": 232,
        "gd": 28
      }
    }
  },
  {
    "game_id": "20260401-LAK-STL",
    "game_time_utc": "2026-04-02 01:00:00+00:00",
    "game_date": "2026-04-01",
    "final": "Final/OT",
    "outcome": "win",
    "location": "Home",
    "score": [
      2,
      1
    ],
    "opponent": {
      "id": "STL",
      "name": "St. Louis Blues",
      "stats": {
        "gp": 79,
        "w": 34,
        "l": 33,
        "t": 0,
        "otl": 12,
        "pts": 80,
        "pct": 0.50633,
        "stk": "W1",
        "gf": 213,
        "ga": 247,
        "gd": -34
      }
    }
  },
  {
    "game_id": "20260402-LAK-NSH",
    "game_time_utc": "2026-04-03 02:30:00+00:00",
    "game_date": "2026-04-02",
    "final": "Final/SO",
    "outcome": "loss",
    "location": "Home",
    "score": [
      4,
      5
    ],
    "opponent": {
      "id": "NSH",
      "name": "Nashville Predators",
      "stats": {
        "gp": 80,
        "w": 38,
        "l": 32,
        "t": 0,
        "otl": 10,
        "pts": 86,
        "pct": 0.5375,
        "stk": "W1",
        "gf": 241,
        "ga": 261,
        "gd": -20
      }
    }
  },
  {
    "game_id": "20260404-LAK-TOR",
    "game_time_utc": "2026-04-04 23:00:00+00:00",
    "game_date": "2026-04-04",
    "final": "Final/OT",
    "outcome": "win",
    "location": "Home",
    "score": [
      7,
      6
    ],
    "opponent": {
      "id": "TOR",
      "name": "Toronto Maple Leafs",
      "stats": {
        "gp": 80,
        "w": 32,
        "l": 34,
        "t": 0,
        "otl": 14,
        "pts": 78,
        "pct": 0.4875,
        "stk": "L3",
        "gf": 247,
        "ga": 290,
        "gd": -43
      }
    }
  },
  {
    "game_id": "20260406-LAK-NSH",
    "game_time_utc": "2026-04-07 02:30:00+00:00",
    "game_date": "2026-04-06",
    "final": "Final/SO",
    "outcome": "win",
    "location": "Home",
    "score": [
      3,
      2
    ],
    "opponent": {
      "id": "NSH",
      "name": "Nashville Predators",
      "stats": {
        "gp": 80,
        "w": 38,
        "l": 32,
        "t": 0,
        "otl": 10,
        "pts": 86,
        "pct": 0.5375,
        "stk": "W1",
        "gf": 241,
        "ga": 261,
        "gd": -20
      }
    }
  },
  {
    "game_id": "20260409-LAK-VAN",
    "game_time_utc": "2026-04-10 02:30:00+00:00",
    "game_date": "2026-04-09",
    "final": "Final",
    "outcome": "win",
    "location": "Home",
    "score": [
      4,
      1
    ],
    "opponent": {
      "id": "VAN",
      "name": "Vancouver Canucks",
      "stats": {
        "gp": 80,
        "w": 24,
        "l": 48,
        "t": 0,
        "otl": 8,
        "pts": 56,
        "pct": 0.35,
        "stk": "W2",
        "gf": 211,
        "ga": 307,
        "gd": -96
      }
    }
  },
  {
    "game_id": "20260411-LAK-EDM",
    "game_time_utc": "2026-04-11 20:00:00+00:00",
    "game_date": "2026-04-11",
    "final": "Final",
    "outcome": "win",
    "location": "Home",
    "score": [
      1,
      0
    ],
    "opponent": {
      "id": "EDM",
      "name": "Edmonton Oilers",
      "stats": {
        "gp": 80,
        "w": 40,
        "l": 30,
        "t": 0,
        "otl": 10,
        "pts": 90,
        "pct": 0.5625,
        "stk": "L1",
        "gf": 275,
        "ga": 266,
        "gd": 9
      }
    }
  },
  {
    "game_id": "20260413-SEA-LAK",
    "game_time_utc": "2026-04-14 01:30:00+00:00",
    "game_date": "2026-04-13",
    "final": "",
    "location": "Away",
    "outcome": "upcoming",
    "score": [
      "",
      ""
    ],
    "opponent": {
      "id": "SEA",
      "name": "Seattle Kraken",
      "stats": {
        "gp": 79,
        "w": 34,
        "l": 34,
        "t": 0,
        "otl": 11,
        "pts": 79,
        "pct": 0.5,
        "stk": "W2",
        "gf": 222,
        "ga": 252,
        "gd": -30
      }
    }
  },
  {
    "game_id": "20260414-VAN-LAK",
    "game_time_utc": "2026-04-15 02:00:00+00:00",
    "game_date": "2026-04-14",
    "final": "",
    "location": "Away",
    "outcome": "upcoming",
    "score": [
      "",
      ""
    ],
    "opponent": {
      "id": "VAN",
      "name": "Vancouver Canucks",
      "stats": {
        "gp": 80,
        "w": 24,
        "l": 48,
        "t": 0,
        "otl": 8,
        "pts": 56,
        "pct": 0.35,
        "stk": "W2",
        "gf": 211,
        "ga": 307,
        "gd": -96
      }
    }
  },
  {
    "game_id": "20260416-CGY-LAK",
    "game_time_utc": "2026-04-17 01:00:00+00:00",
    "game_date": "2026-04-16",
    "final": "",
    "location": "Away",
    "outcome": "upcoming",
    "score": [
      "",
      ""
    ],
    "opponent": {
      "id": "CGY",
      "name": "Calgary Flames",
      "stats": {
        "gp": 80,
        "w": 33,
        "l": 38,
        "t": 0,
        "otl": 9,
        "pts": 75,
        "pct": 0.46875,
        "stk": "W1",
        "gf": 208,
        "ga": 255,
        "gd": -47
      }
    }
  }
]